[
{"start_time":0.0,"end_time":2.6,"span":{"text":"魯迅雜文集\n熱風","speech":"魯迅雜文集\n熱風"},"total_cost":81.821,"advance_i":158,"advance_j":91,"average_over_min":0.8893587,"subalignments":[{"start_time":0.0,"end_time":1.66,"span":{"text":"魯迅雜文集\n","speech":"魯迅雜文集\n"},"total_cost":55.229034,"advance_i":98,"advance_j":68,"average_over_min":0.80042076,"subalignments":[{"start_time":0.0,"end_time":0.9,"span":{"text":"魯迅","speech":"魯迅"},"total_cost":29.095568,"advance_i":45,"advance_j":28,"average_over_min":1.0032954,"subalignments":[]},{"start_time":0.9,"end_time":1.18,"span":{"text":"雜","speech":"雜"},"total_cost":9.909742,"advance_i":15,"advance_j":17,"average_over_min":0.6193589,"subalignments":[]},{"start_time":1.2,"end_time":1.64,"span":{"text":"文集","speech":"文集"},"total_cost":15.222946,"advance_i":22,"advance_j":29,"average_over_min":0.6618672,"subalignments":[]},{"start_time":1.64,"end_time":1.64,"span":{"text":"\n","speech":"\n"},"total_cost":0.42102814,"advance_i":1,"advance_j":1,"average_over_min":0.21051407,"subalignments":[]}]},{"start_time":1.96,"end_time":2.58,"span":{"text":"熱風","speech":"熱風"},"total_cost":22.954529,"advance_i":32,"advance_j":28,"average_over_min":0.7915355,"subalignments":[{"start_time":1.96,"end_time":2.56,"span":{"text":"熱風","speech":"熱風"},"total_cost":22.419987,"advance_i":31,"advance_j":28,"average_over_min":0.773103,"subalignments":[]}]}]},
{"start_time":3.16,"end_time":4.5,"span":{"text":"隨感錄四十七","speech":"隨感錄四十七"},"total_cost":41.958878,"advance_i":93,"advance_j":75,"average_over_min":0.55209047,"subalignments":[{"start_time":3.16,"end_time":4.48,"span":{"text":"隨感錄四十七","speech":"隨感錄四十七"},"total_cost":42.066338,"advance_i":67,"advance_j":75,"average_over_min":0.6186226,"subalignments":[{"start_time":3.16,"end_time":3.4,"span":{"text":"隨","speech":"隨"},"total_cost":11.035687,"advance_i":13,"advance_j":16,"average_over_min":0.7882634,"subalignments":[]},{"start_time":3.42,"end_time":3.56,"span":{"text":"感","speech":"感"},"total_cost":7.4031897,"advance_i":8,"advance_j":17,"average_over_min":0.82257664,"subalignments":[]},{"start_time":3.58,"end_time":3.72,"span":{"text":"錄","speech":"錄"},"total_cost":6.422636,"advance_i":8,"advance_j":13,"average_over_min":0.7136262,"subalignments":[]},{"start_time":3.74,"end_time":4.0,"span":{"text":"四","speech":"四"},"total_cost":10.280527,"advance_i":13,"advance_j":14,"average_over_min":0.7343234,"subalignments":[]},{"start_time":4.0,"end_time":4.46,"span":{"text":"十七","speech":"十七"},"total_cost":14.630795,"advance_i":24,"advance_j":29,"average_over_min":0.5852318,"subalignments":[]}]}]},
{"start_time":5.02,"end_time":7.16,"span":{"text":"此次 LibriVox 錄音由公眾所有。","speech":"此次 LibriVox 錄音由公眾所有。"},"total_cost":80.95799,"advance_i":107,"advance_j":147,"average_over_min":0.749611,"subalignments":[{"start_time":5.02,"end_time":7.14,"span":{"text":"此次 LibriVox 錄音由公眾所有。","speech":"此次 LibriVox 錄音由公眾所有。"},"total_cost":81.963196,"advance_i":107,"advance_j":147,"average_over_min":0.75891846,"subalignments":[{"start_time":5.02,"end_time":5.48,"span":{"text":"此次","speech":"此次"},"total_cost":19.742348,"advance_i":24,"advance_j":27,"average_over_min":0.7896939,"subalignments":[]},{"start_time":5.5,"end_time":5.5,"span":{"text":" ","speech":" "},"total_cost":0.6745949,"advance_i":1,"advance_j":1,"average_over_min":0.33729744,"subalignments":[]},{"start_time":5.52,"end_time":6.0,"span":{"text":"LibriVox","speech":"LibriVox"},"total_cost":18.371464,"advance_i":25,"advance_j":35,"average_over_min":0.70659477,"subalignments":[]},{"start_time":6.02,"end_time":6.02,"span":{"text":" ","speech":" "},"total_cost":1.0,"advance_i":1,"advance_j":1,"average_over_min":0.5,"subalignments":[]},{"start_time":6.04,"end_time":6.36,"span":{"text":"錄音","speech":"錄音"},"total_cost":12.424759,"advance_i":17,"advance_j":27,"average_over_min":0.6902644,"subalignments":[]},{"start_time":6.38,"end_time":6.52,"span":{"text":"由","speech":"由"},"total_cost":6.226452,"advance_i":8,"advance_j":15,"average_over_min":0.691828,"subalignments":[]},{"start_time":6.54,"end_time":6.86,"span":{"text":"公眾","speech":"公眾"},"total_cost":15.417126,"advance_i":17,"advance_j":33,"average_over_min":0.856507,"subalignments":[]},{"start_time":6.88,"end_time":7.12,"span":{"text":"所有","speech":"所有"},"total_cost":19.211342,"advance_i":12,"advance_j":29,"average_over_min":1.4777955,"subalignments":[]},{"start_time":7.12,"end_time":7.12,"span":{"text":"。","speech":"。"},"total_cost":1.0,"advance_i":1,"advance_j":1,"average_over_min":0.5,"subalignments":[]}]}]},
{"start_time":7.16,"end_time":31.94,"span":{"text":"有人做了一塊象牙片，半寸方，看去也沒有什麼；用顯微鏡一照，卻看見刻著一篇行書的《蘭亭序》。我想：顯微鏡的所以製造，本為看那些極細微的自然物的；現在既用人工，何妨便刻在一塊半尺方的象牙板上，一目了然，省卻用顯微鏡的工夫呢?","speech":"有人做了一塊象牙片，半寸方，看去也沒有什麼；用顯微鏡一照，卻看見刻著一篇行書的《蘭亭序》。我想：顯微鏡的所以製造，本為看那些極細微的自然物的；現在既用人工，何妨便刻在一塊半尺方的象牙板上，一目了然，省卻用顯微鏡的工夫呢?"},"total_cost":760.37695,"advance_i":1250,"advance_j":1168,"average_over_min":0.65045077,"subalignments":[{"start_time":7.16,"end_time":17.82,"span":{"text":"有人做了一塊象牙片，半寸方，看去也沒有什麼；用顯微鏡一照，卻看見刻著一篇行書的《蘭亭序》。","speech":"有人做了一塊象牙片，半寸方，看去也沒有什麼；用顯微鏡一照，卻看見刻著一篇行書的《蘭亭序》。"},"total_cost":326.5746,"advance_i":571,"advance_j":477,"average_over_min":0.68321043,"subalignments":[{"start_time":7.16,"end_time":7.54,"span":{"text":"有人","speech":"有人"},"total_cost":21.272352,"advance_i":98,"advance_j":28,"average_over_min":0.7335294,"subalignments":[]},{"start_time":9.12,"end_time":9.42,"span":{"text":"做了","speech":"做了"},"total_cost":13.964663,"advance_i":16,"advance_j":21,"average_over_min":0.8214507,"subalignments":[]},{"start_time":9.44,"end_time":9.86,"span":{"text":"一塊","speech":"一塊"},"total_cost":16.444313,"advance_i":22,"advance_j":23,"average_over_min":0.7149701,"subalignments":[]},{"start_time":9.88,"end_time":10.54,"span":{"text":"象牙","speech":"象牙"},"total_cost":28.064041,"advance_i":34,"advance_j":33,"average_over_min":0.825413,"subalignments":[]},{"start_time":10.56,"end_time":10.94,"span":{"text":"片","speech":"片"},"total_cost":10.97982,"advance_i":20,"advance_j":15,"average_over_min":0.68623877,"subalignments":[]},{"start_time":11.12,"end_time":11.12,"span":{"text":"，","speech":"，"},"total_cost":0.03263855,"advance_i":8,"advance_j":1,"average_over_min":0.016319275,"subalignments":[]},{"start_time":11.12,"end_time":11.28,"span":{"text":"半","speech":"半"},"total_cost":8.326378,"advance_i":9,"advance_j":14,"average_over_min":0.8326378,"subalignments":[]},{"start_time":11.3,"end_time":11.54,"span":{"text":"寸","speech":"寸"},"total_cost":11.091843,"advance_i":13,"advance_j":17,"average_over_min":0.7922745,"subalignments":[]},{"start_time":11.56,"end_time":11.84,"span":{"text":"方","speech":"方"},"total_cost":10.646317,"advance_i":14,"advance_j":18,"average_over_min":0.7097544,"subalignments":[]},{"start_time":11.84,"end_time":11.84,"span":{"text":"，","speech":"，"},"total_cost":0.012123108,"advance_i":0,"advance_j":1,"average_over_min":0.012123108,"subalignments":[]},{"start_time":11.84,"end_time":12.64,"span":{"text":"看去","speech":"看去"},"total_cost":26.791992,"advance_i":41,"advance_j":31,"average_over_min":0.83724976,"subalignments":[]},{"start_time":12.66,"end_time":13.04,"span":{"text":"也沒有","speech":"也沒有"},"total_cost":19.294662,"advance_i":20,"advance_j":36,"average_over_min":0.91879344,"subalignments":[]},{"start_time":13.06,"end_time":13.46,"span":{"text":"什麼","speech":"什麼"},"total_cost":16.268326,"advance_i":25,"advance_j":25,"average_over_min":0.6257048,"subalignments":[]},{"start_time":13.56,"end_time":13.56,"span":{"text":"；","speech":"；"},"total_cost":0.10292053,"advance_i":1,"advance_j":1,"average_over_min":0.051460266,"subalignments":[]},{"start_time":13.62,"end_time":13.92,"span":{"text":"用","speech":"用"},"total_cost":11.548233,"advance_i":18,"advance_j":14,"average_over_min":0.7698822,"subalignments":[]},{"start_time":13.94,"end_time":14.52,"span":{"text":"顯微鏡","speech":"顯微鏡"},"total_cost":25.385498,"advance_i":30,"advance_j":43,"average_over_min":0.81888705,"subalignments":[]},{"start_time":14.54,"end_time":14.64,"span":{"text":"一","speech":"一"},"total_cost":5.2596893,"advance_i":6,"advance_j":12,"average_over_min":0.7513842,"subalignments":[]},{"start_time":14.66,"end_time":14.96,"span":{"text":"照","speech":"照"},"total_cost":14.722092,"advance_i":24,"advance_j":14,"average_over_min":0.9814728,"subalignments":[]},{"start_time":15.14,"end_time":15.14,"span":{"text":"，","speech":"，"},"total_cost":0.0,"advance_i":1,"advance_j":1,"average_over_min":0.0,"subalignments":[]},{"start_time":15.16,"end_time":15.32,"span":{"text":"卻","speech":"卻"},"total_cost":5.9943237,"advance_i":9,"advance_j":16,"average_over_min":0.59943235,"subalignments":[]},{"start_time":15.34,"end_time":15.86,"span":{"text":"看見","speech":"看見"},"total_cost":20.047073,"advance_i":28,"advance_j":31,"average_over_min":0.6912784,"subalignments":[]},{"start_time":15.9,"end_time":16.16,"span":{"text":"刻著","speech":"刻著"},"total_cost":17.65564,"advance_i":13,"advance_j":23,"average_over_min":1.2611171,"subalignments":[]},{"start_time":16.16,"end_time":16.3,"span":{"text":"一篇","speech":"一篇"},"total_cost":13.203339,"advance_i":7,"advance_j":25,"average_over_min":1.6504173,"subalignments":[]},{"start_time":16.3,"end_time":16.78,"span":{"text":"行","speech":"行"},"total_cost":10.994751,"advance_i":25,"advance_j":20,"average_over_min":0.5235596,"subalignments":[]},{"start_time":16.8,"end_time":16.98,"span":{"text":"書","speech":"書"},"total_cost":6.625641,"advance_i":9,"advance_j":15,"average_over_min":0.6625641,"subalignments":[]},{"start_time":16.98,"end_time":16.98,"span":{"text":"的","speech":"的"},"total_cost":6.643463,"advance_i":0,"advance_j":8,"average_over_min":6.643463,"subalignments":[]},{"start_time":16.98,"end_time":16.98,"span":{"text":"《","speech":"《"},"total_cost":0.3647766,"advance_i":0,"advance_j":1,"average_over_min":0.3647766,"subalignments":[]},{"start_time":16.98,"end_time":17.24,"span":{"text":"蘭","speech":"蘭"},"total_cost":11.639404,"advance_i":14,"advance_j":18,"average_over_min":0.77596027,"subalignments":[]},{"start_time":17.26,"end_time":17.44,"span":{"text":"亭","speech":"亭"},"total_cost":9.580688,"advance_i":10,"advance_j":19,"average_over_min":0.8709717,"subalignments":[]},{"start_time":17.46,"end_time":17.8,"span":{"text":"序","speech":"序"},"total_cost":8.075623,"advance_i":17,"advance_j":16,"average_over_min":0.47503662,"subalignments":[]},{"start_time":17.8,"end_time":17.8,"span":{"text":"》","speech":"》"},"total_cost":0.4498291,"advance_i":0,"advance_j":1,"average_over_min":0.4498291,"subalignments":[]},{"start_time":17.8,"end_time":17.8,"span":{"text":"。","speech":"。"},"total_cost":0.4498291,"advance_i":1,"advance_j":1,"average_over_min":0.22491455,"subalignments":[]}]},{"start_time":18.58,"end_time":31.92,"span":{"text":"我想：顯微鏡的所以製造，本為看那些極細微的自然物的；現在既用人工，何妨便刻在一塊半尺方的象牙板上，一目了然，省卻用顯微鏡的工夫呢?","speech":"我想：顯微鏡的所以製造，本為看那些極細微的自然物的；現在既用人工，何妨便刻在一塊半尺方的象牙板上，一目了然，省卻用顯微鏡的工夫呢?"},"total_cost":436.53558,"advance_i":668,"advance_j":694,"average_over_min":0.6525196,"subalignments":[{"start_time":18.58,"end_time":18.98,"span":{"text":"我想","speech":"我想"},"total_cost":14.684443,"advance_i":21,"advance_j":30,"average_over_min":0.6674747,"subalignments":[]},{"start_time":19.02,"end_time":19.02,"span":{"text":"：","speech":"："},"total_cost":0.0,"advance_i":2,"advance_j":1,"average_over_min":0.0,"subalignments":[]},{"start_time":19.04,"end_time":19.82,"span":{"text":"顯微鏡","speech":"顯微鏡"},"total_cost":24.329792,"advance_i":39,"advance_j":43,"average_over_min":0.6082448,"subalignments":[]},{"start_time":19.82,"end_time":19.9,"span":{"text":"的","speech":"的"},"total_cost":6.959095,"advance_i":5,"advance_j":8,"average_over_min":1.1598492,"subalignments":[]},{"start_time":19.92,"end_time":20.28,"span":{"text":"所以","speech":"所以"},"total_cost":13.391563,"advance_i":18,"advance_j":29,"average_over_min":0.70481914,"subalignments":[]},{"start_time":20.28,"end_time":20.74,"span":{"text":"製造","speech":"製造"},"total_cost":12.824253,"advance_i":23,"advance_j":25,"average_over_min":0.5343439,"subalignments":[]},{"start_time":20.74,"end_time":20.74,"span":{"text":"，","speech":"，"},"total_cost":0.03591919,"advance_i":0,"advance_j":1,"average_over_min":0.03591919,"subalignments":[]},{"start_time":20.74,"end_time":20.78,"span":{"text":"本","speech":"本"},"total_cost":11.166313,"advance_i":2,"advance_j":17,"average_over_min":3.7221043,"subalignments":[]},{"start_time":20.78,"end_time":20.92,"span":{"text":"為","speech":"為"},"total_cost":9.0731735,"advance_i":10,"advance_j":13,"average_over_min":0.8248339,"subalignments":[]},{"start_time":20.98,"end_time":21.1,"span":{"text":"看","speech":"看"},"total_cost":8.664055,"advance_i":6,"advance_j":16,"average_over_min":1.2377222,"subalignments":[]},{"start_time":21.1,"end_time":21.52,"span":{"text":"那些","speech":"那些"},"total_cost":14.540855,"advance_i":22,"advance_j":26,"average_over_min":0.6322111,"subalignments":[]},{"start_time":21.54,"end_time":22.22,"span":{"text":"極細","speech":"極細"},"total_cost":10.698708,"advance_i":35,"advance_j":27,"average_over_min":0.3820967,"subalignments":[]},{"start_time":22.24,"end_time":22.4,"span":{"text":"微","speech":"微"},"total_cost":6.310402,"advance_i":8,"advance_j":12,"average_over_min":0.7011558,"subalignments":[]},{"start_time":22.4,"end_time":22.46,"span":{"text":"的","speech":"的"},"total_cost":5.663849,"advance_i":4,"advance_j":8,"average_over_min":1.1327698,"subalignments":[]},{"start_time":22.48,"end_time":22.92,"span":{"text":"自然","speech":"自然"},"total_cost":21.148682,"advance_i":22,"advance_j":32,"average_over_min":0.9195079,"subalignments":[]},{"start_time":22.92,"end_time":23.04,"span":{"text":"物","speech":"物"},"total_cost":4.081711,"advance_i":7,"advance_j":12,"average_over_min":0.51021385,"subalignments":[]},{"start_time":23.06,"end_time":23.52,"span":{"text":"的","speech":"的"},"total_cost":13.172913,"advance_i":24,"advance_j":8,"average_over_min":1.4636569,"subalignments":[]},{"start_time":23.54,"end_time":23.54,"span":{"text":"；","speech":"；"},"total_cost":0.0,"advance_i":1,"advance_j":1,"average_over_min":0.0,"subalignments":[]},{"start_time":23.56,"end_time":24.02,"span":{"text":"現在","speech":"現在"},"total_cost":15.004272,"advance_i":24,"advance_j":30,"average_over_min":0.6001709,"subalignments":[]},{"start_time":24.04,"end_time":24.22,"span":{"text":"既","speech":"既"},"total_cost":6.005356,"advance_i":9,"advance_j":13,"average_over_min":0.6005356,"subalignments":[]},{"start_time":24.22,"end_time":24.36,"span":{"text":"用","speech":"用"},"total_cost":10.893036,"advance_i":7,"advance_j":14,"average_over_min":1.3616295,"subalignments":[]},{"start_time":24.36,"end_time":24.78,"span":{"text":"人工","speech":"人工"},"total_cost":13.80719,"advance_i":22,"advance_j":27,"average_over_min":0.6003126,"subalignments":[]},{"start_time":24.8,"end_time":24.8,"span":{"text":"，","speech":"，"},"total_cost":0.21650696,"advance_i":1,"advance_j":1,"average_over_min":0.10825348,"subalignments":[]},{"start_time":24.82,"end_time":25.5,"span":{"text":"何妨","speech":"何妨"},"total_cost":20.25998,"advance_i":34,"advance_j":31,"average_over_min":0.63312435,"subalignments":[]},{"start_time":25.5,"end_time":25.68,"span":{"text":"便","speech":"便"},"total_cost":8.520676,"advance_i":9,"advance_j":14,"average_over_min":0.8520676,"subalignments":[]},{"start_time":25.68,"end_time":25.94,"span":{"text":"刻在","speech":"刻在"},"total_cost":20.271835,"advance_i":14,"advance_j":26,"average_over_min":1.3514557,"subalignments":[]},{"start_time":25.96,"end_time":26.4,"span":{"text":"一塊","speech":"一塊"},"total_cost":15.467346,"advance_i":22,"advance_j":23,"average_over_min":0.67249334,"subalignments":[]},{"start_time":26.4,"end_time":26.56,"span":{"text":"半","speech":"半"},"total_cost":8.595337,"advance_i":9,"advance_j":14,"average_over_min":0.85953367,"subalignments":[]},{"start_time":26.58,"end_time":26.72,"span":{"text":"尺","speech":"尺"},"total_cost":9.188202,"advance_i":8,"advance_j":17,"average_over_min":1.0209113,"subalignments":[]},{"start_time":26.74,"end_time":26.96,"span":{"text":"方","speech":"方"},"total_cost":7.795105,"advance_i":12,"advance_j":18,"average_over_min":0.59962344,"subalignments":[]},{"start_time":26.98,"end_time":27.18,"span":{"text":"的","speech":"的"},"total_cost":7.1589355,"advance_i":11,"advance_j":8,"average_over_min":0.7954373,"subalignments":[]},{"start_time":27.2,"end_time":27.78,"span":{"text":"象牙","speech":"象牙"},"total_cost":27.410675,"advance_i":29,"advance_j":33,"average_over_min":0.9136892,"subalignments":[]},{"start_time":27.78,"end_time":27.84,"span":{"text":"板","speech":"板"},"total_cost":7.3236694,"advance_i":4,"advance_j":17,"average_over_min":1.4647338,"subalignments":[]},{"start_time":27.86,"end_time":28.04,"span":{"text":"上","speech":"上"},"total_cost":12.005005,"advance_i":10,"advance_j":18,"average_over_min":1.091364,"subalignments":[]},{"start_time":28.08,"end_time":28.08,"span":{"text":"，","speech":"，"},"total_cost":0.0008544922,"advance_i":2,"advance_j":1,"average_over_min":0.0004272461,"subalignments":[]},{"start_time":28.1,"end_time":28.9,"span":{"text":"一目了然","speech":"一目了然"},"total_cost":23.53241,"advance_i":40,"advance_j":46,"average_over_min":0.5739612,"subalignments":[]},{"start_time":28.9,"end_time":28.9,"span":{"text":"，","speech":"，"},"total_cost":0.0,"advance_i":0,"advance_j":1,"average_over_min":0.0,"subalignments":[]},{"start_time":28.9,"end_time":29.5,"span":{"text":"省卻","speech":"省卻"},"total_cost":16.656006,"advance_i":30,"advance_j":31,"average_over_min":0.5372905,"subalignments":[]},{"start_time":29.5,"end_time":29.7,"span":{"text":"用","speech":"用"},"total_cost":10.8526,"advance_i":11,"advance_j":14,"average_over_min":0.90438336,"subalignments":[]},{"start_time":29.72,"end_time":30.52,"span":{"text":"顯微鏡","speech":"顯微鏡"},"total_cost":29.422638,"advance_i":41,"advance_j":43,"average_over_min":0.700539,"subalignments":[]},{"start_time":30.54,"end_time":30.74,"span":{"text":"的","speech":"的"},"total_cost":6.816284,"advance_i":11,"advance_j":8,"average_over_min":0.7573649,"subalignments":[]},{"start_time":30.76,"end_time":31.84,"span":{"text":"工夫","speech":"工夫"},"total_cost":29.15805,"advance_i":54,"advance_j":26,"average_over_min":1.0799278,"subalignments":[]},{"start_time":31.84,"end_time":31.88,"span":{"text":"呢","speech":"呢"},"total_cost":5.112549,"advance_i":3,"advance_j":8,"average_over_min":1.2781372,"subalignments":[]},{"start_time":31.9,"end_time":31.9,"span":{"text":"?","speech":"?"},"total_cost":0.48944092,"advance_i":1,"advance_j":1,"average_over_min":0.24472046,"subalignments":[]}]}]},
{"start_time":32.16,"end_time":54.94,"span":{"text":"張三李四是同時人。張三記了古典來做古文；李四又記了古典，去讀張三做的古文。我想：古典是古人的時事，要曉得那時的事，所以免不了翻著古典；現在兩位既然同時，何妨老實說出，一目瞭然，省卻你也記古典，我也記古典的工夫呢?","speech":"張三李四是同時人。張三記了古典來做古文；李四又記了古典，去讀張三做的古文。我想：古典是古人的時事，要曉得那時的事，所以免不了翻著古典；現在兩位既然同時，何妨老實說出，一目瞭然，省卻你也記古典，我也記古典的工夫呢?"},"total_cost":667.29095,"advance_i":1238,"advance_j":1109,"average_over_min":0.601163,"subalignments":[{"start_time":32.16,"end_time":34.42,"span":{"text":"張三李四是同時人。","speech":"張三李四是同時人。"},"total_cost":74.823975,"advance_i":120,"advance_j":113,"average_over_min":0.6563507,"subalignments":[{"start_time":32.16,"end_time":33.08,"span":{"text":"張三李四","speech":"張三李四"},"total_cost":35.161747,"advance_i":47,"advance_j":55,"average_over_min":0.7325364,"subalignments":[]},{"start_time":33.1,"end_time":33.36,"span":{"text":"是","speech":"是"},"total_cost":9.289467,"advance_i":13,"advance_j":15,"average_over_min":0.66353333,"subalignments":[]},{"start_time":33.36,"end_time":34.06,"span":{"text":"同時","speech":"同時"},"total_cost":23.141582,"advance_i":36,"advance_j":33,"average_over_min":0.6806348,"subalignments":[]},{"start_time":34.14,"end_time":34.4,"span":{"text":"人","speech":"人"},"total_cost":12.608971,"advance_i":16,"advance_j":19,"average_over_min":0.74170417,"subalignments":[]},{"start_time":34.4,"end_time":34.4,"span":{"text":"。","speech":"。"},"total_cost":0.52323914,"advance_i":1,"advance_j":1,"average_over_min":0.26161957,"subalignments":[]}]},{"start_time":34.56,"end_time":41.14,"span":{"text":"張三記了古典來做古文；李四又記了古典，去讀張三做的古文。","speech":"張三記了古典來做古文；李四又記了古典，去讀張三做的古文。"},"total_cost":193.06161,"advance_i":329,"advance_j":291,"average_over_min":0.6611699,"subalignments":[{"start_time":34.56,"end_time":34.78,"span":{"text":"張","speech":"張"},"total_cost":10.154752,"advance_i":12,"advance_j":18,"average_over_min":0.7811347,"subalignments":[]},{"start_time":34.8,"end_time":35.12,"span":{"text":"三","speech":"三"},"total_cost":9.82746,"advance_i":16,"advance_j":17,"average_over_min":0.5780859,"subalignments":[]},{"start_time":35.12,"end_time":35.26,"span":{"text":"記","speech":"記"},"total_cost":4.8390636,"advance_i":7,"advance_j":13,"average_over_min":0.60488296,"subalignments":[]},{"start_time":35.26,"end_time":35.38,"span":{"text":"了","speech":"了"},"total_cost":7.4284115,"advance_i":11,"advance_j":9,"average_over_min":0.7428411,"subalignments":[]},{"start_time":35.48,"end_time":35.74,"span":{"text":"古典","speech":"古典"},"total_cost":14.06691,"advance_i":13,"advance_j":25,"average_over_min":1.0047792,"subalignments":[]},{"start_time":35.74,"end_time":36.02,"span":{"text":"來","speech":"來"},"total_cost":9.353607,"advance_i":15,"advance_j":15,"average_over_min":0.58460045,"subalignments":[]},{"start_time":36.04,"end_time":36.22,"span":{"text":"做","speech":"做"},"total_cost":9.110329,"advance_i":10,"advance_j":15,"average_over_min":0.8282117,"subalignments":[]},{"start_time":36.24,"end_time":36.72,"span":{"text":"古文","speech":"古文"},"total_cost":14.505554,"advance_i":25,"advance_j":25,"average_over_min":0.5579059,"subalignments":[]},{"start_time":36.84,"end_time":36.84,"span":{"text":"；","speech":"；"},"total_cost":0.10445404,"advance_i":6,"advance_j":1,"average_over_min":0.05222702,"subalignments":[]},{"start_time":36.86,"end_time":37.1,"span":{"text":"李","speech":"李"},"total_cost":12.091194,"advance_i":15,"advance_j":15,"average_over_min":0.75569963,"subalignments":[]},{"start_time":37.16,"end_time":37.52,"span":{"text":"四","speech":"四"},"total_cost":13.442856,"advance_i":19,"advance_j":14,"average_over_min":0.8961904,"subalignments":[]},{"start_time":37.54,"end_time":37.78,"span":{"text":"又","speech":"又"},"total_cost":10.622963,"advance_i":12,"advance_j":13,"average_over_min":0.817151,"subalignments":[]},{"start_time":37.78,"end_time":37.94,"span":{"text":"記","speech":"記"},"total_cost":5.407852,"advance_i":8,"advance_j":13,"average_over_min":0.60087246,"subalignments":[]},{"start_time":37.94,"end_time":38.06,"span":{"text":"了","speech":"了"},"total_cost":6.7939453,"advance_i":8,"advance_j":9,"average_over_min":0.7548828,"subalignments":[]},{"start_time":38.1,"end_time":38.54,"span":{"text":"古典","speech":"古典"},"total_cost":12.234535,"advance_i":23,"advance_j":25,"average_over_min":0.5097723,"subalignments":[]},{"start_time":38.56,"end_time":38.56,"span":{"text":"，","speech":"，"},"total_cost":0.0,"advance_i":1,"advance_j":1,"average_over_min":0.0,"subalignments":[]},{"start_time":38.58,"end_time":38.7,"span":{"text":"去","speech":"去"},"total_cost":6.1195526,"advance_i":8,"advance_j":16,"average_over_min":0.6799503,"subalignments":[]},{"start_time":38.74,"end_time":39.04,"span":{"text":"讀","speech":"讀"},"total_cost":9.312683,"advance_i":16,"advance_j":14,"average_over_min":0.62084556,"subalignments":[]},{"start_time":39.06,"end_time":39.32,"span":{"text":"張","speech":"張"},"total_cost":10.076248,"advance_i":14,"advance_j":18,"average_over_min":0.6717499,"subalignments":[]},{"start_time":39.34,"end_time":39.52,"span":{"text":"三","speech":"三"},"total_cost":8.021805,"advance_i":10,"advance_j":17,"average_over_min":0.72925496,"subalignments":[]},{"start_time":39.54,"end_time":39.86,"span":{"text":"做的","speech":"做的"},"total_cost":16.001083,"advance_i":16,"advance_j":20,"average_over_min":0.9412402,"subalignments":[]},{"start_time":39.86,"end_time":40.26,"span":{"text":"古文","speech":"古文"},"total_cost":15.132309,"advance_i":22,"advance_j":25,"average_over_min":0.6579265,"subalignments":[]},{"start_time":41.12,"end_time":41.12,"span":{"text":"。","speech":"。"},"total_cost":0.5302582,"advance_i":42,"advance_j":1,"average_over_min":0.2651291,"subalignments":[]}]},{"start_time":41.14,"end_time":54.84,"span":{"text":"我想：古典是古人的時事，要曉得那時的事，所以免不了翻著古典；現在兩位既然同時，何妨老實說出，一目瞭然，省卻你也記古典，我也記古典的工夫呢?","speech":"我想：古典是古人的時事，要曉得那時的事，所以免不了翻著古典；現在兩位既然同時，何妨老實說出，一目瞭然，省卻你也記古典，我也記古典的工夫呢?"},"total_cost":413.19327,"advance_i":690,"advance_j":707,"average_over_min":0.5979642,"subalignments":[{"start_time":41.14,"end_time":41.56,"span":{"text":"我想","speech":"我想"},"total_cost":15.633048,"advance_i":22,"advance_j":30,"average_over_min":0.67969775,"subalignments":[]},{"start_time":41.94,"end_time":41.94,"span":{"text":"：","speech":"："},"total_cost":0.745265,"advance_i":18,"advance_j":1,"average_over_min":0.3726325,"subalignments":[]},{"start_time":41.94,"end_time":42.16,"span":{"text":"古典","speech":"古典"},"total_cost":10.039608,"advance_i":11,"advance_j":25,"average_over_min":0.836634,"subalignments":[]},{"start_time":42.16,"end_time":42.6,"span":{"text":"是","speech":"是"},"total_cost":13.011934,"advance_i":23,"advance_j":15,"average_over_min":0.8132459,"subalignments":[]},{"start_time":42.62,"end_time":42.94,"span":{"text":"古人","speech":"古人"},"total_cost":14.590027,"advance_i":17,"advance_j":27,"average_over_min":0.81055707,"subalignments":[]},{"start_time":42.96,"end_time":43.02,"span":{"text":"的","speech":"的"},"total_cost":5.26062,"advance_i":4,"advance_j":8,"average_over_min":1.052124,"subalignments":[]},{"start_time":43.04,"end_time":43.56,"span":{"text":"時事","speech":"時事"},"total_cost":12.694344,"advance_i":27,"advance_j":27,"average_over_min":0.4533694,"subalignments":[]},{"start_time":43.6,"end_time":43.6,"span":{"text":"，","speech":"，"},"total_cost":0.035064697,"advance_i":2,"advance_j":1,"average_over_min":0.017532349,"subalignments":[]},{"start_time":43.62,"end_time":43.96,"span":{"text":"要","speech":"要"},"total_cost":14.6475525,"advance_i":19,"advance_j":13,"average_over_min":1.0462538,"subalignments":[]},{"start_time":44.0,"end_time":44.4,"span":{"text":"曉得","speech":"曉得"},"total_cost":15.71077,"advance_i":20,"advance_j":25,"average_over_min":0.7481319,"subalignments":[]},{"start_time":44.4,"end_time":44.8,"span":{"text":"那時","speech":"那時"},"total_cost":16.288574,"advance_i":21,"advance_j":27,"average_over_min":0.74038976,"subalignments":[]},{"start_time":44.82,"end_time":45.08,"span":{"text":"的","speech":"的"},"total_cost":7.228241,"advance_i":15,"advance_j":8,"average_over_min":0.8031379,"subalignments":[]},{"start_time":45.12,"end_time":45.26,"span":{"text":"事","speech":"事"},"total_cost":6.056999,"advance_i":9,"advance_j":15,"average_over_min":0.6056999,"subalignments":[]},{"start_time":45.3,"end_time":45.3,"span":{"text":"，","speech":"，"},"total_cost":0.0,"advance_i":0,"advance_j":1,"average_over_min":0.0,"subalignments":[]},{"start_time":45.3,"end_time":45.58,"span":{"text":"所以","speech":"所以"},"total_cost":13.242249,"advance_i":15,"advance_j":29,"average_over_min":0.82764053,"subalignments":[]},{"start_time":45.6,"end_time":46.08,"span":{"text":"免不了","speech":"免不了"},"total_cost":21.647583,"advance_i":25,"advance_j":31,"average_over_min":0.83259934,"subalignments":[]},{"start_time":46.1,"end_time":46.34,"span":{"text":"翻","speech":"翻"},"total_cost":10.449402,"advance_i":13,"advance_j":17,"average_over_min":0.7463859,"subalignments":[]},{"start_time":46.36,"end_time":46.44,"span":{"text":"著","speech":"著"},"total_cost":6.4869843,"advance_i":5,"advance_j":11,"average_over_min":1.081164,"subalignments":[]},{"start_time":46.46,"end_time":46.94,"span":{"text":"古典","speech":"古典"},"total_cost":16.904343,"advance_i":45,"advance_j":25,"average_over_min":0.65016705,"subalignments":[]},{"start_time":47.36,"end_time":47.36,"span":{"text":"；","speech":"；"},"total_cost":0.0,"advance_i":0,"advance_j":1,"average_over_min":0.0,"subalignments":[]},{"start_time":47.36,"end_time":47.82,"span":{"text":"現在","speech":"現在"},"total_cost":13.516129,"advance_i":24,"advance_j":30,"average_over_min":0.5406451,"subalignments":[]},{"start_time":47.84,"end_time":48.12,"span":{"text":"兩位","speech":"兩位"},"total_cost":15.198898,"advance_i":15,"advance_j":27,"average_over_min":0.94993114,"subalignments":[]},{"start_time":48.14,"end_time":48.5,"span":{"text":"既然","speech":"既然"},"total_cost":16.56247,"advance_i":19,"advance_j":31,"average_over_min":0.82812345,"subalignments":[]},{"start_time":48.52,"end_time":49.26,"span":{"text":"同時","speech":"同時"},"total_cost":21.626099,"advance_i":38,"advance_j":33,"average_over_min":0.6360617,"subalignments":[]},{"start_time":49.28,"end_time":49.28,"span":{"text":"，","speech":"，"},"total_cost":0.0012207031,"advance_i":1,"advance_j":1,"average_over_min":0.00061035156,"subalignments":[]},{"start_time":49.3,"end_time":49.86,"span":{"text":"何妨","speech":"何妨"},"total_cost":17.810059,"advance_i":28,"advance_j":31,"average_over_min":0.61414,"subalignments":[]},{"start_time":49.86,"end_time":50.2,"span":{"text":"老實說","speech":"老實說"},"total_cost":17.841644,"advance_i":18,"advance_j":40,"average_over_min":0.9390339,"subalignments":[]},{"start_time":50.22,"end_time":50.48,"span":{"text":"出","speech":"出"},"total_cost":5.4339294,"advance_i":14,"advance_j":14,"average_over_min":0.36226195,"subalignments":[]},{"start_time":50.5,"end_time":50.5,"span":{"text":"，","speech":"，"},"total_cost":0.0,"advance_i":1,"advance_j":1,"average_over_min":0.0,"subalignments":[]},{"start_time":50.52,"end_time":51.46,"span":{"text":"一目瞭然","speech":"一目瞭然"},"total_cost":31.166443,"advance_i":48,"advance_j":51,"average_over_min":0.63604987,"subalignments":[]},{"start_time":51.5,"end_time":51.5,"span":{"text":"，","speech":"，"},"total_cost":0.000061035156,"advance_i":2,"advance_j":1,"average_over_min":0.000030517578,"subalignments":[]},{"start_time":51.52,"end_time":51.92,"span":{"text":"省卻","speech":"省卻"},"total_cost":14.509003,"advance_i":21,"advance_j":31,"average_over_min":0.6595001,"subalignments":[]},{"start_time":51.94,"end_time":52.12,"span":{"text":"你","speech":"你"},"total_cost":7.491333,"advance_i":9,"advance_j":15,"average_over_min":0.7491333,"subalignments":[]},{"start_time":52.12,"end_time":52.34,"span":{"text":"也","speech":"也"},"total_cost":8.372314,"advance_i":12,"advance_j":15,"average_over_min":0.6440242,"subalignments":[]},{"start_time":52.36,"end_time":52.8,"span":{"text":"記","speech":"記"},"total_cost":8.625977,"advance_i":25,"advance_j":13,"average_over_min":0.6161412,"subalignments":[]},{"start_time":52.86,"end_time":53.28,"span":{"text":"古典","speech":"古典"},"total_cost":12.138367,"advance_i":27,"advance_j":25,"average_over_min":0.46686026,"subalignments":[]},{"start_time":53.4,"end_time":53.4,"span":{"text":"，","speech":"，"},"total_cost":0.0,"advance_i":1,"advance_j":1,"average_over_min":0.0,"subalignments":[]},{"start_time":53.42,"end_time":53.72,"span":{"text":"我也","speech":"我也"},"total_cost":13.059418,"advance_i":16,"advance_j":27,"average_over_min":0.76820105,"subalignments":[]},{"start_time":53.74,"end_time":53.92,"span":{"text":"記","speech":"記"},"total_cost":5.5507507,"advance_i":9,"advance_j":13,"average_over_min":0.55507505,"subalignments":[]},{"start_time":53.92,"end_time":54.1,"span":{"text":"古典","speech":"古典"},"total_cost":10.77179,"advance_i":9,"advance_j":25,"average_over_min":1.077179,"subalignments":[]},{"start_time":54.1,"end_time":54.34,"span":{"text":"的","speech":"的"},"total_cost":9.398071,"advance_i":13,"advance_j":8,"average_over_min":1.0442301,"subalignments":[]},{"start_time":54.36,"end_time":54.68,"span":{"text":"工夫","speech":"工夫"},"total_cost":9.343079,"advance_i":17,"advance_j":26,"average_over_min":0.5190599,"subalignments":[]},{"start_time":54.7,"end_time":54.8,"span":{"text":"呢","speech":"呢"},"total_cost":5.983734,"advance_i":6,"advance_j":8,"average_over_min":0.8548192,"subalignments":[]},{"start_time":54.82,"end_time":54.82,"span":{"text":"?","speech":"?"},"total_cost":1.0,"advance_i":1,"advance_j":1,"average_over_min":0.5,"subalignments":[]}]}]},
{"start_time":56.92,"end_time":61.26,"span":{"text":"內行的人說：什麼話！這是本領，是學問！","speech":"內行的人說：什麼話！這是本領，是學問！"},"total_cost":138.04846,"advance_i":218,"advance_j":198,"average_over_min":0.69371086,"subalignments":[{"start_time":56.92,"end_time":58.82,"span":{"text":"內行的人說：什麼話！","speech":"內行的人說：什麼話！"},"total_cost":65.766335,"advance_i":96,"advance_j":103,"average_over_min":0.67800343,"subalignments":[{"start_time":56.92,"end_time":56.96,"span":{"text":"內","speech":"內"},"total_cost":5.7520747,"advance_i":3,"advance_j":13,"average_over_min":1.4380187,"subalignments":[]},{"start_time":56.98,"end_time":57.24,"span":{"text":"行","speech":"行"},"total_cost":15.676605,"advance_i":14,"advance_j":20,"average_over_min":1.045107,"subalignments":[]},{"start_time":57.26,"end_time":57.32,"span":{"text":"的","speech":"的"},"total_cost":5.68882,"advance_i":4,"advance_j":8,"average_over_min":1.137764,"subalignments":[]},{"start_time":57.34,"end_time":57.5,"span":{"text":"人","speech":"人"},"total_cost":14.315792,"advance_i":9,"advance_j":19,"average_over_min":1.4315792,"subalignments":[]},{"start_time":57.52,"end_time":57.78,"span":{"text":"說","speech":"說"},"total_cost":13.217506,"advance_i":29,"advance_j":18,"average_over_min":0.6956582,"subalignments":[]},{"start_time":58.1,"end_time":58.1,"span":{"text":"：","speech":"："},"total_cost":0.0,"advance_i":0,"advance_j":1,"average_over_min":0.0,"subalignments":[]},{"start_time":58.1,"end_time":58.64,"span":{"text":"什麼","speech":"什麼"},"total_cost":17.425083,"advance_i":27,"advance_j":25,"average_over_min":0.6701955,"subalignments":[]},{"start_time":58.64,"end_time":58.8,"span":{"text":"話","speech":"話"},"total_cost":9.440773,"advance_i":8,"advance_j":18,"average_over_min":1.0489748,"subalignments":[]},{"start_time":58.8,"end_time":58.8,"span":{"text":"！","speech":"！"},"total_cost":1.0,"advance_i":1,"advance_j":1,"average_over_min":0.5,"subalignments":[]}]},{"start_time":58.84,"end_time":61.24,"span":{"text":"這是本領，是學問！","speech":"這是本領，是學問！"},"total_cost":71.282524,"advance_i":121,"advance_j":96,"average_over_min":0.7348714,"subalignments":[{"start_time":58.84,"end_time":59.6,"span":{"text":"這是","speech":"這是"},"total_cost":22.24331,"advance_i":39,"advance_j":27,"average_over_min":0.794404,"subalignments":[]},{"start_time":59.62,"end_time":60.18,"span":{"text":"本領","speech":"本領"},"total_cost":25.256876,"advance_i":36,"advance_j":31,"average_over_min":0.7892774,"subalignments":[]},{"start_time":60.34,"end_time":60.34,"span":{"text":"，","speech":"，"},"total_cost":0.0,"advance_i":1,"advance_j":1,"average_over_min":0.0,"subalignments":[]},{"start_time":60.36,"end_time":60.56,"span":{"text":"是","speech":"是"},"total_cost":7.7417526,"advance_i":11,"advance_j":15,"average_over_min":0.6451461,"subalignments":[]},{"start_time":60.58,"end_time":61.2,"span":{"text":"學問","speech":"學問"},"total_cost":18.314243,"advance_i":32,"advance_j":27,"average_over_min":0.6540801,"subalignments":[]},{"start_time":61.22,"end_time":61.22,"span":{"text":"！","speech":"！"},"total_cost":1.0,"advance_i":1,"advance_j":1,"average_over_min":0.5,"subalignments":[]}]}]},
{"start_time":61.3,"end_time":80.92,"span":{"text":"我想，幸而中國人中，有這一類本領學問的人還不多。倘若誰也弄這玄虛：農夫送來了一粒粉，用顯微鏡照了，卻是一碗飯；水夫挑來用水濕過的土，想喝茶的又須擠出濕土裡的水：那可真要支撐不住了。","speech":"我想，幸而中國人中，有這一類本領學問的人還不多。倘若誰也弄這玄虛：農夫送來了一粒粉，用顯微鏡照了，卻是一碗飯；水夫挑來用水濕過的土，想喝茶的又須擠出濕土裡的水：那可真要支撐不住了。"},"total_cost":638.2704,"advance_i":1045,"advance_j":979,"average_over_min":0.6512963,"subalignments":[{"start_time":61.3,"end_time":66.68,"span":{"text":"我想，幸而中國人中，有這一類本領學問的人還不多。","speech":"我想，幸而中國人中，有這一類本領學問的人還不多。"},"total_cost":176.21173,"advance_i":270,"advance_j":262,"average_over_min":0.6700066,"subalignments":[{"start_time":61.3,"end_time":62.6,"span":{"text":"我想","speech":"我想"},"total_cost":29.032768,"advance_i":66,"advance_j":30,"average_over_min":0.9365409,"subalignments":[]},{"start_time":62.66,"end_time":62.66,"span":{"text":"，","speech":"，"},"total_cost":0.0012893677,"advance_i":3,"advance_j":1,"average_over_min":0.00064468384,"subalignments":[]},{"start_time":62.68,"end_time":63.18,"span":{"text":"幸而","speech":"幸而"},"total_cost":24.655151,"advance_i":26,"advance_j":32,"average_over_min":0.91315377,"subalignments":[]},{"start_time":63.2,"end_time":63.52,"span":{"text":"中國","speech":"中國"},"total_cost":11.923744,"advance_i":17,"advance_j":31,"average_over_min":0.6624302,"subalignments":[]},{"start_time":63.54,"end_time":64.04,"span":{"text":"人中","speech":"人中"},"total_cost":16.055023,"advance_i":25,"advance_j":31,"average_over_min":0.6175009,"subalignments":[]},{"start_time":64.04,"end_time":64.04,"span":{"text":"，","speech":"，"},"total_cost":0.004272461,"advance_i":1,"advance_j":1,"average_over_min":0.0021362305,"subalignments":[]},{"start_time":64.06,"end_time":64.3,"span":{"text":"有","speech":"有"},"total_cost":12.327209,"advance_i":13,"advance_j":15,"average_over_min":0.880515,"subalignments":[]},{"start_time":64.32,"end_time":64.74,"span":{"text":"這一","speech":"這一"},"total_cost":16.378845,"advance_i":22,"advance_j":25,"average_over_min":0.7121237,"subalignments":[]},{"start_time":64.76,"end_time":65.0,"span":{"text":"類","speech":"類"},"total_cost":6.603058,"advance_i":13,"advance_j":13,"average_over_min":0.471647,"subalignments":[]},{"start_time":65.02,"end_time":65.3,"span":{"text":"本領","speech":"本領"},"total_cost":18.696083,"advance_i":15,"advance_j":31,"average_over_min":1.1685052,"subalignments":[]},{"start_time":65.32,"end_time":65.68,"span":{"text":"學問","speech":"學問"},"total_cost":13.47287,"advance_i":18,"advance_j":27,"average_over_min":0.7090984,"subalignments":[]},{"start_time":65.68,"end_time":65.68,"span":{"text":"的","speech":"的"},"total_cost":6.8186646,"advance_i":0,"advance_j":8,"average_over_min":6.8186646,"subalignments":[]},{"start_time":65.68,"end_time":65.98,"span":{"text":"人","speech":"人"},"total_cost":14.708664,"advance_i":16,"advance_j":19,"average_over_min":0.86521554,"subalignments":[]},{"start_time":66.0,"end_time":66.44,"span":{"text":"還不","speech":"還不"},"total_cost":15.364075,"advance_i":23,"advance_j":24,"average_over_min":0.6401698,"subalignments":[]},{"start_time":66.46,"end_time":66.64,"span":{"text":"多","speech":"多"},"total_cost":6.329361,"advance_i":10,"advance_j":12,"average_over_min":0.5753965,"subalignments":[]},{"start_time":66.66,"end_time":66.66,"span":{"text":"。","speech":"。"},"total_cost":1.0,"advance_i":1,"advance_j":1,"average_over_min":0.5,"subalignments":[]}]},{"start_time":66.7,"end_time":80.9,"span":{"text":"倘若誰也弄這玄虛：農夫送來了一粒粉，用顯微鏡照了，卻是一碗飯；水夫挑來用水濕過的土，想喝茶的又須擠出濕土裡的水：那可真要支撐不住了。","speech":"倘若誰也弄這玄虛：農夫送來了一粒粉，用顯微鏡照了，卻是一碗飯；水夫挑來用水濕過的土，想喝茶的又須擠出濕土裡的水：那可真要支撐不住了。"},"total_cost":457.58417,"advance_i":711,"advance_j":715,"average_over_min":0.6426744,"subalignments":[{"start_time":66.7,"end_time":67.28,"span":{"text":"倘若","speech":"倘若"},"total_cost":25.419302,"advance_i":29,"advance_j":29,"average_over_min":0.84731007,"subalignments":[]},{"start_time":67.28,"end_time":67.78,"span":{"text":"誰","speech":"誰"},"total_cost":14.823668,"advance_i":26,"advance_j":20,"average_over_min":0.7058889,"subalignments":[]},{"start_time":67.8,"end_time":68.0,"span":{"text":"也","speech":"也"},"total_cost":7.3893547,"advance_i":11,"advance_j":15,"average_over_min":0.6157796,"subalignments":[]},{"start_time":68.02,"end_time":68.24,"span":{"text":"弄","speech":"弄"},"total_cost":8.563839,"advance_i":12,"advance_j":15,"average_over_min":0.65875685,"subalignments":[]},{"start_time":68.26,"end_time":68.56,"span":{"text":"這","speech":"這"},"total_cost":9.504223,"advance_i":16,"advance_j":14,"average_over_min":0.63361484,"subalignments":[]},{"start_time":68.58,"end_time":69.1,"span":{"text":"玄虛","speech":"玄虛"},"total_cost":15.832779,"advance_i":33,"advance_j":33,"average_over_min":0.46566996,"subalignments":[]},{"start_time":69.24,"end_time":69.24,"span":{"text":"：","speech":"："},"total_cost":0.01436615,"advance_i":1,"advance_j":1,"average_over_min":0.007183075,"subalignments":[]},{"start_time":69.26,"end_time":69.78,"span":{"text":"農夫","speech":"農夫"},"total_cost":12.230301,"advance_i":27,"advance_j":26,"average_over_min":0.4529741,"subalignments":[]},{"start_time":69.8,"end_time":70.26,"span":{"text":"送來","speech":"送來"},"total_cost":24.518875,"advance_i":24,"advance_j":33,"average_over_min":0.98075503,"subalignments":[]},{"start_time":70.28,"end_time":70.44,"span":{"text":"了","speech":"了"},"total_cost":8.225006,"advance_i":9,"advance_j":9,"average_over_min":0.8225006,"subalignments":[]},{"start_time":70.46,"end_time":70.58,"span":{"text":"一粒","speech":"一粒"},"total_cost":10.6026,"advance_i":6,"advance_j":22,"average_over_min":1.5146571,"subalignments":[]},{"start_time":70.58,"end_time":70.9,"span":{"text":"粉","speech":"粉"},"total_cost":14.272324,"advance_i":17,"advance_j":19,"average_over_min":0.7929069,"subalignments":[]},{"start_time":70.92,"end_time":70.92,"span":{"text":"，","speech":"，"},"total_cost":0.14144897,"advance_i":1,"advance_j":1,"average_over_min":0.07072449,"subalignments":[]},{"start_time":70.94,"end_time":71.22,"span":{"text":"用","speech":"用"},"total_cost":11.545639,"advance_i":15,"advance_j":14,"average_over_min":0.7697093,"subalignments":[]},{"start_time":71.24,"end_time":71.82,"span":{"text":"顯微鏡","speech":"顯微鏡"},"total_cost":25.593964,"advance_i":29,"advance_j":43,"average_over_min":0.8531321,"subalignments":[]},{"start_time":71.82,"end_time":72.3,"span":{"text":"照了","speech":"照了"},"total_cost":16.27533,"advance_i":29,"advance_j":20,"average_over_min":0.7750157,"subalignments":[]},{"start_time":72.4,"end_time":72.4,"span":{"text":"，","speech":"，"},"total_cost":0.0,"advance_i":0,"advance_j":1,"average_over_min":0.0,"subalignments":[]},{"start_time":72.4,"end_time":72.66,"span":{"text":"卻是","speech":"卻是"},"total_cost":12.245529,"advance_i":14,"advance_j":28,"average_over_min":0.81636864,"subalignments":[]},{"start_time":72.68,"end_time":72.8,"span":{"text":"一","speech":"一"},"total_cost":5.782608,"advance_i":7,"advance_j":12,"average_over_min":0.722826,"subalignments":[]},{"start_time":72.82,"end_time":73.32,"span":{"text":"碗飯","speech":"碗飯"},"total_cost":16.456238,"advance_i":28,"advance_j":30,"average_over_min":0.5674565,"subalignments":[]},{"start_time":73.76,"end_time":73.76,"span":{"text":"；","speech":"；"},"total_cost":0.07305908,"advance_i":19,"advance_j":1,"average_over_min":0.03652954,"subalignments":[]},{"start_time":73.76,"end_time":74.34,"span":{"text":"水夫","speech":"水夫"},"total_cost":13.337372,"advance_i":30,"advance_j":27,"average_over_min":0.47633472,"subalignments":[]},{"start_time":74.36,"end_time":74.6,"span":{"text":"挑","speech":"挑"},"total_cost":9.8311615,"advance_i":12,"advance_j":16,"average_over_min":0.75624317,"subalignments":[]},{"start_time":74.6,"end_time":74.78,"span":{"text":"來","speech":"來"},"total_cost":8.906586,"advance_i":10,"advance_j":15,"average_over_min":0.8096896,"subalignments":[]},{"start_time":74.8,"end_time":75.1,"span":{"text":"用水","speech":"用水"},"total_cost":20.41626,"advance_i":16,"advance_j":32,"average_over_min":1.2009565,"subalignments":[]},{"start_time":75.12,"end_time":75.42,"span":{"text":"濕","speech":"濕"},"total_cost":10.270569,"advance_i":16,"advance_j":15,"average_over_min":0.64191055,"subalignments":[]},{"start_time":75.44,"end_time":75.52,"span":{"text":"過","speech":"過"},"total_cost":8.195648,"advance_i":5,"advance_j":11,"average_over_min":1.3659414,"subalignments":[]},{"start_time":75.54,"end_time":75.64,"span":{"text":"的","speech":"的"},"total_cost":5.8490295,"advance_i":6,"advance_j":8,"average_over_min":0.83557564,"subalignments":[]},{"start_time":75.66,"end_time":75.9,"span":{"text":"土","speech":"土"},"total_cost":9.743378,"advance_i":25,"advance_j":15,"average_over_min":0.6089611,"subalignments":[]},{"start_time":76.16,"end_time":76.16,"span":{"text":"，","speech":"，"},"total_cost":0.0,"advance_i":0,"advance_j":1,"average_over_min":0.0,"subalignments":[]},{"start_time":76.16,"end_time":76.38,"span":{"text":"想","speech":"想"},"total_cost":11.970367,"advance_i":12,"advance_j":20,"average_over_min":0.92079747,"subalignments":[]},{"start_time":76.4,"end_time":76.86,"span":{"text":"喝茶","speech":"喝茶"},"total_cost":20.306854,"advance_i":24,"advance_j":29,"average_over_min":0.81227416,"subalignments":[]},{"start_time":76.88,"end_time":77.02,"span":{"text":"的","speech":"的"},"total_cost":8.687225,"advance_i":8,"advance_j":8,"average_over_min":0.9652473,"subalignments":[]},{"start_time":77.04,"end_time":77.18,"span":{"text":"又","speech":"又"},"total_cost":8.844086,"advance_i":8,"advance_j":13,"average_over_min":0.9826762,"subalignments":[]},{"start_time":77.2,"end_time":77.34,"span":{"text":"須","speech":"須"},"total_cost":7.9651184,"advance_i":7,"advance_j":15,"average_over_min":0.9956398,"subalignments":[]},{"start_time":77.34,"end_time":77.78,"span":{"text":"擠出","speech":"擠出"},"total_cost":12.014984,"advance_i":23,"advance_j":25,"average_over_min":0.50062436,"subalignments":[]},{"start_time":77.8,"end_time":77.96,"span":{"text":"濕","speech":"濕"},"total_cost":7.33374,"advance_i":9,"advance_j":15,"average_over_min":0.733374,"subalignments":[]},{"start_time":77.98,"end_time":78.32,"span":{"text":"土裡","speech":"土裡"},"total_cost":9.492859,"advance_i":18,"advance_j":19,"average_over_min":0.49962416,"subalignments":[]},{"start_time":78.34,"end_time":78.7,"span":{"text":"的","speech":"的"},"total_cost":10.138947,"advance_i":25,"advance_j":8,"average_over_min":1.1265496,"subalignments":[]},{"start_time":78.84,"end_time":79.14,"span":{"text":"水","speech":"水"},"total_cost":12.716187,"advance_i":16,"advance_j":20,"average_over_min":0.748011,"subalignments":[]},{"start_time":79.16,"end_time":79.16,"span":{"text":"：","speech":"："},"total_cost":1.0,"advance_i":1,"advance_j":1,"average_over_min":0.5,"subalignments":[]},{"start_time":79.18,"end_time":79.42,"span":{"text":"那","speech":"那"},"total_cost":11.482971,"advance_i":14,"advance_j":13,"average_over_min":0.82021224,"subalignments":[]},{"start_time":79.46,"end_time":79.98,"span":{"text":"可真要","speech":"可真要"},"total_cost":24.365814,"advance_i":26,"advance_j":39,"average_over_min":0.90243757,"subalignments":[]},{"start_time":79.98,"end_time":80.4,"span":{"text":"支撐","speech":"支撐"},"total_cost":12.49173,"advance_i":22,"advance_j":30,"average_over_min":0.54311866,"subalignments":[]},{"start_time":80.42,"end_time":80.74,"span":{"text":"不住","speech":"不住"},"total_cost":9.922546,"advance_i":17,"advance_j":25,"average_over_min":0.5512526,"subalignments":[]},{"start_time":80.76,"end_time":80.86,"span":{"text":"了","speech":"了"},"total_cost":7.103485,"advance_i":6,"advance_j":9,"average_over_min":1.0147836,"subalignments":[]},{"start_time":80.88,"end_time":80.88,"span":{"text":"。","speech":"。"},"total_cost":1.0,"advance_i":1,"advance_j":1,"average_over_min":0.5,"subalignments":[]}]}]},
{"start_time":82.18,"end_time":84.16,"span":{"text":"隨感錄四十七\n結束","speech":"隨感錄四十七\n結束"},"total_cost":60.182373,"advance_i":418,"advance_j":98,"average_over_min":0.60790277,"subalignments":[{"start_time":82.18,"end_time":83.64,"span":{"text":"隨感錄四十七\n","speech":"隨感錄四十七\n"},"total_cost":40.33465,"advance_i":74,"advance_j":75,"average_over_min":0.5377953,"subalignments":[{"start_time":82.18,"end_time":82.48,"span":{"text":"隨","speech":"隨"},"total_cost":10.23136,"advance_i":16,"advance_j":16,"average_over_min":0.6018447,"subalignments":[]},{"start_time":82.5,"end_time":82.72,"span":{"text":"感","speech":"感"},"total_cost":8.057141,"advance_i":12,"advance_j":17,"average_over_min":0.6197801,"subalignments":[]},{"start_time":82.74,"end_time":82.94,"span":{"text":"錄","speech":"錄"},"total_cost":6.7108994,"advance_i":11,"advance_j":13,"average_over_min":0.5592416,"subalignments":[]},{"start_time":82.96,"end_time":83.22,"span":{"text":"四","speech":"四"},"total_cost":11.070187,"advance_i":13,"advance_j":14,"average_over_min":0.7907276,"subalignments":[]},{"start_time":83.22,"end_time":83.62,"span":{"text":"十七","speech":"十七"},"total_cost":11.978821,"advance_i":20,"advance_j":29,"average_over_min":0.57042,"subalignments":[]},{"start_time":83.62,"end_time":83.62,"span":{"text":"\n","speech":"\n"},"total_cost":1.0,"advance_i":1,"advance_j":1,"average_over_min":0.5,"subalignments":[]}]},{"start_time":83.66,"end_time":84.14,"span":{"text":"結束","speech":"結束"},"total_cost":12.078617,"advance_i":25,"advance_j":26,"average_over_min":0.4645622,"subalignments":[{"start_time":83.66,"end_time":84.12,"span":{"text":"結束","speech":"結束"},"total_cost":12.145912,"advance_i":24,"advance_j":26,"average_over_min":0.48583648,"subalignments":[]}]}]},
{"start_time":90.54,"end_time":90.54,"span":{"text":"","speech":""},"total_cost":0.0,"advance_i":1,"advance_j":1,"average_over_min":0.0,"subalignments":[]}]
